django_cachex/__init__.py
django_cachex/cache.py
django_cachex/compat.py
django_cachex/exceptions.py
django_cachex/omit_exception.py
django_cachex/py.typed
django_cachex/script.py
django_cachex/types.py
django_cachex/util.py
django_cachex/client/__init__.py
django_cachex/client/cache.py
django_cachex/client/cluster.py
django_cachex/client/default.py
django_cachex/client/pipeline.py
django_cachex/client/sentinel.py
django_cachex/compressors/__init__.py
django_cachex/compressors/base.py
django_cachex/compressors/gzip.py
django_cachex/compressors/lz4.py
django_cachex/compressors/lzma.py
django_cachex/compressors/zlib.py
django_cachex/compressors/zstd.py
django_cachex/serializers/__init__.py
django_cachex/serializers/base.py
django_cachex/serializers/json.py
django_cachex/serializers/msgpack.py
django_cachex/serializers/pickle.py
django_cachex-0.1.0b3.dist-info/METADATA
django_cachex-0.1.0b3.dist-info/WHEEL
django_cachex-0.1.0b3.dist-info/licenses/LICENSE
django_cachex-0.1.0b3.dist-info/RECORD
