Metadata-Version: 2.4
Name: django-cachex
Version: 0.1.0b3
Summary: Full featured Valkey and Redis cache backend for Django
Project-URL: Homepage, https://github.com/oliverhaas/django-cachex
Project-URL: Documentation, https://oliverhaas.github.io/django-cachex/
Project-URL: Repository, https://github.com/oliverhaas/django-cachex.git
Project-URL: Changelog, https://oliverhaas.github.io/django-cachex/reference/changelog/
Author-email: Oliver Haas <ohaas@e1plus.de>
License: MIT
License-File: LICENSE
Keywords: backend,cache,django,redis,valkey
Classifier: Development Status :: 4 - Beta
Classifier: Environment :: Web Environment
Classifier: Framework :: Django
Classifier: Framework :: Django :: 5.2
Classifier: Framework :: Django :: 6.0
Classifier: Intended Audience :: Developers
Classifier: License :: OSI Approved :: MIT License
Classifier: Operating System :: OS Independent
Classifier: Programming Language :: Python
Classifier: Programming Language :: Python :: 3
Classifier: Programming Language :: Python :: 3 :: Only
Classifier: Programming Language :: Python :: 3.12
Classifier: Programming Language :: Python :: 3.13
Classifier: Programming Language :: Python :: 3.14
Classifier: Topic :: Internet :: WWW/HTTP
Classifier: Topic :: Software Development :: Libraries
Classifier: Topic :: Utilities
Classifier: Typing :: Typed
Requires-Python: >=3.12
Requires-Dist: django<7,>=5.2
Provides-Extra: hiredis
Requires-Dist: redis[hiredis]<8,>=6; extra == 'hiredis'
Provides-Extra: libvalkey
Requires-Dist: valkey[libvalkey]<7,>=6.1.0; extra == 'libvalkey'
Provides-Extra: lz4
Requires-Dist: lz4>=4.4.0; extra == 'lz4'
Provides-Extra: msgpack
Requires-Dist: msgpack>=1.1.0; extra == 'msgpack'
Provides-Extra: redis
Requires-Dist: redis<8,>=6; extra == 'redis'
Provides-Extra: valkey
Requires-Dist: valkey<7,>=6.1.0; extra == 'valkey'
Provides-Extra: zstd
Requires-Dist: backports-zstd>=1.3.0; (python_version < '3.14') and extra == 'zstd'
